aristaproto/__init__.py
aristaproto/_types.py
aristaproto/_version.py
aristaproto/casing.py
aristaproto/compile/__init__.py
aristaproto/compile/importing.py
aristaproto/compile/naming.py
aristaproto/enum.py
aristaproto/grpc/__init__.py
aristaproto/grpc/grpclib_client.py
aristaproto/grpc/grpclib_server.py
aristaproto/grpc/util/__init__.py
aristaproto/grpc/util/async_channel.py
aristaproto/lib/__init__.py
aristaproto/lib/google/__init__.py
aristaproto/lib/google/protobuf/__init__.py
aristaproto/lib/google/protobuf/compiler/__init__.py
aristaproto/lib/pydantic/__init__.py
aristaproto/lib/pydantic/google/__init__.py
aristaproto/lib/pydantic/google/protobuf/__init__.py
aristaproto/lib/pydantic/google/protobuf/compiler/__init__.py
aristaproto/lib/std/__init__.py
aristaproto/lib/std/google/__init__.py
aristaproto/lib/std/google/protobuf/__init__.py
aristaproto/lib/std/google/protobuf/compiler/__init__.py
aristaproto/plugin/__init__.py
aristaproto/plugin/__main__.py
aristaproto/plugin/compiler.py
aristaproto/plugin/main.py
aristaproto/plugin/models.py
aristaproto/plugin/module_validation.py
aristaproto/plugin/parser.py
aristaproto/plugin/plugin.bat
aristaproto/plugin/typing_compiler.py
aristaproto/py.typed
aristaproto/templates/header.py.j2
aristaproto/templates/template.py.j2
aristaproto/utils.py
aristaproto-0.1.4.dist-info/LICENSE.md
aristaproto-0.1.4.dist-info/METADATA
aristaproto-0.1.4.dist-info/WHEEL
aristaproto-0.1.4.dist-info/entry_points.txt
aristaproto-0.1.4.dist-info/RECORD
