Metadata-Version: 2.1
Name: aristaproto
Version: 0.1.4
Summary: Arista Protobuf / Python gRPC bindings generator & library
Home-page: https://github.com/aristanetworks/python-aristaproto
License: MIT
Keywords: protobuf,gRPC,aristanetworks,arista
Author: Arista Networks
Author-email: ansible@arista.com
Requires-Python: >=3.9,<4.0
Classifier: License :: OSI Approved :: MIT License
Classifier: Programming Language :: Python :: 3
Classifier: Programming Language :: Python :: 3.9
Classifier: Programming Language :: Python :: 3.10
Classifier: Programming Language :: Python :: 3.11
Classifier: Programming Language :: Python :: 3.12
Classifier: Programming Language :: Python :: 3.13
Provides-Extra: compiler
Provides-Extra: rust-codec
Requires-Dist: betterproto-rust-codec (==0.1.1) ; extra == "rust-codec"
Requires-Dist: grpclib (>=0.4.1,<0.5.0)
Requires-Dist: jinja2 (>=3.0.3) ; extra == "compiler"
Requires-Dist: python-dateutil (>=2.8,<3.0)
Requires-Dist: ruff (>=0.11.11) ; extra == "compiler"
Requires-Dist: typing-extensions (>=4.7.1,<5.0.0)
Project-URL: Repository, https://github.com/aristanetworks/python-aristaproto
